resource_translate/__init__.py
resource_translate/utils.py
resource_translate-1.2.0.dist-info/LICENSE
resource_translate-1.2.0.dist-info/METADATA
resource_translate-1.2.0.dist-info/WHEEL
resource_translate-1.2.0.dist-info/top_level.txt
resource_translate-1.2.0.dist-info/RECORD
