Metadata-Version: 2.1
Name: resource-translate
Version: 1.2.0
Summary: Utilities to translate resources between platforms.
Home-page: https://github.com/austinbravodev/resource_translate
Author: Austin Bravo
Author-email: austinbravo@hey.com
License: Apache 2.0
Keywords: API,integration,resources,translation
Platform: UNKNOWN
Classifier: Operating System :: OS Independent
Classifier: Programming Language :: Python :: 3
Classifier: Programming Language :: Python :: 3.7
Requires-Python: >=3.7
